pyDRTtools/BHT.py
pyDRTtools/GUI.py
pyDRTtools/HMC.py
pyDRTtools/__init__.py
pyDRTtools/basics.py
pyDRTtools/cli.py
pyDRTtools/layout.py
pyDRTtools/runs.py
pyDRTtools-0.2.0.90.dist-info/LICENSE
pyDRTtools-0.2.0.90.dist-info/METADATA
pyDRTtools-0.2.0.90.dist-info/WHEEL
pyDRTtools-0.2.0.90.dist-info/entry_points.txt
pyDRTtools-0.2.0.90.dist-info/top_level.txt
pyDRTtools-0.2.0.90.dist-info/RECORD
