Metadata-Version: 2.1
Name: pyDRTtools
Version: 0.2.0.90
Summary: pyDRTtools: A Python-based DRTtools to Deconvolve the Distribution of Relaxation Times from Electrochemical Impedance Spectroscopy Data
Home-page: https://github.com/ciuccislab/pyDRTtools
Author: ciuccislab
Author-email: amaradesa@connect.ust.hk
Project-URL: Source Code, https://github.com/ciuccislab/pyDRTtools
Project-URL: Bug Tracker, https://github.com/ciuccislab/pyDRTtools/issues
Classifier: Programming Language :: Python :: 3
Classifier: Programming Language :: Python :: 3.4
Classifier: Programming Language :: Python :: 3.5
Classifier: Programming Language :: Python :: 3.6
Classifier: Programming Language :: Python :: 3.7
Classifier: Programming Language :: Python :: 3.8
Classifier: Programming Language :: Python :: 3.9
Classifier: Programming Language :: Python :: 3.10
Classifier: License :: OSI Approved :: MIT License
Classifier: Operating System :: OS Independent
Requires-Python: >=3
License-File: LICENSE
Requires-Dist: click
Requires-Dist: ipython
